jkGlyphsHelpers/__init__.py
jkGlyphsHelpers/forAll.py
jkGlyphsHelpers/forSelected.py
jkGlyphsHelpers/file/__init__.py
jkGlyphsHelpers/file/plist.py
jkGlyphsHelpers/file/yaml.py
jkGlyphsHelpers/hintingPS/__init__.py
jkGlyphsHelpers/hintingPS/ocd.py
jkGlyphsHelpers/ui/__init__.py
jkGlyphsHelpers/ui/dialogs.py
jkGlyphsHelpers-0.1.0.dist-info/LICENSE
jkGlyphsHelpers-0.1.0.dist-info/METADATA
jkGlyphsHelpers-0.1.0.dist-info/WHEEL
jkGlyphsHelpers-0.1.0.dist-info/top_level.txt
jkGlyphsHelpers-0.1.0.dist-info/RECORD
