Metadata-Version: 2.1
Name: jkGlyphsHelpers
Version: 0.1.0
Summary: Helper modules for GlyphsApp scripts.
Home-page: https://github.com/jenskutilek/jkGlyphsHelpers
Author: Jens Kutilek
Classifier: Programming Language :: Python :: 3
Classifier: Operating System :: OS Independent
Classifier: Environment :: Console
Requires-Python: >=3.8
License-File: LICENSE
Requires-Dist: pyyaml>=6.0.1
